phrasegen/__init__.py
phrasegen/api.py
phrasegen/defaults.py
phrasegen/version.py
phrasegen/wordlist/cs
phrasegen/wordlist/en
phrasegen/wordlist/es
phrasegen/wordlist/fr
phrasegen/wordlist/it
phrasegen/wordlist/ja
phrasegen/wordlist/ko
phrasegen/wordlist/pt
phrasegen/wordlist/ru
phrasegen/wordlist/tr
phrasegen/wordlist/zh_cn
phrasegen/wordlist/zh_hant
phrasegen-1.1.2.dist-info/LICENSE
phrasegen-1.1.2.dist-info/METADATA
phrasegen-1.1.2.dist-info/WHEEL
phrasegen-1.1.2.dist-info/top_level.txt
phrasegen-1.1.2.dist-info/RECORD
