Metadata-Version: 2.2
Name: phrasegen
Version: 1.1.2
Summary: Dead simple package for generating random Phrases
Author-email: NotStatilko <thenonproton@pm.me>
License: MIT License
Project-URL: Repository, https://github.com/NotStatilko/phrasegen.git
Keywords: Mnemonic,Phrase
License-File: LICENSE
